<?xml version="1.0" encoding="utf-8"?>
<StructureDefinition xmlns="http://hl7.org/fhir">
  <id value="cb26a2d4-7cfc-47c9-b3ef-0bc2cfb8aeb7" />
  <meta>
    <versionId value="3" />
    <lastUpdated value="2021-12-04T09:31:39.347+00:00" />
  </meta>
  <url value="http://jpfhir.jp/fhir/core/Extension/StructureDefinition/JP_MedicationAdministration_DosageSite_SiteComment" />
  <version value="1.0.0" />
  <name value="JP_MedicationAdministration_DosageSite_SiteComment" />
  <title value="JP_MedicationAdministration_DosageSite_SiteComment" />
  <status value="active" />
  <date value="2021-12-04T09:31:36.9391653+00:00" />
  <publisher value="FHIR® Japanese implementation research workaing group in Japan Association of Medical Informatics (JAMI)" />
  <description value="投与部位コメントを格納するための拡張" />
  <purpose value="投与部位コメントを格納するための拡張" />
  <copyright value="FHIR® Japanese implementation research workaing group in Japan Association of Medical Informatics (JAMI)" />
  <fhirVersion value="4.0.1" />
  <kind value="complex-type" />
  <abstract value="false" />
  <context>
    <type value="element" />
    <expression value="MedicationAdministration.dosage.site" />
  </context>
  <type value="Extension" />
  <baseDefinition value="http://hl7.org/fhir/StructureDefinition/Extension" />
  <derivation value="constraint" />
  <differential>
    <element id="Extension.url">
      <path value="Extension.url" />
      <fixedUri value="http://jpfhir.jp/fhir/core/Extension/StructureDefinition/JP_MedicationAdministration_DosageSite_SiteComment" />
    </element>
    <element id="Extension.value[x]">
      <path value="Extension.value[x]" />
      <type>
        <code value="string" />
      </type>
      <type>
        <code value="CodeableConcept" />
      </type>
    </element>
  </differential>
</StructureDefinition>